bilihud/__init__.py
bilihud/__main__.py
bilihud/auth.py
bilihud/danmaku_client.py
bilihud/danmaku_widget.py
bilihud/main.py
bilihud/qr_login_dialog.py
bilihud/utils.py
bilihud/assets/icon.png
bilihud/vendor/blivedm/__init__.py
bilihud/vendor/blivedm/handlers.py
bilihud/vendor/blivedm/utils.py
bilihud/vendor/blivedm/clients/__init__.py
bilihud/vendor/blivedm/clients/open_live.py
bilihud/vendor/blivedm/clients/web.py
bilihud/vendor/blivedm/clients/ws_base.py
bilihud/vendor/blivedm/models/__init__.py
bilihud/vendor/blivedm/models/open_live.py
bilihud/vendor/blivedm/models/pb.py
bilihud/vendor/blivedm/models/web.py
bilihud-0.2.0.dist-info/METADATA
bilihud-0.2.0.dist-info/WHEEL
bilihud-0.2.0.dist-info/entry_points.txt
bilihud-0.2.0.dist-info/licenses/LICENSE
bilihud-0.2.0.dist-info/RECORD
