Metadata-Version: 2.4
Name: bilihud
Version: 0.2.0
Summary: B站弹幕阅读器 - 一个可以在游戏全屏时显示弹幕的Qt应用程序
Project-URL: bugs, https://github.com/locez/bilihud/issues
Project-URL: changelog, https://github.com/locez/bilihud/blob/master/changelog.md
Project-URL: homepage, https://github.com/locez/bilihud
Author-email: Locez <locez@locez.com>
Maintainer-email: Locez <locez@locez.com>
License: MIT
License-File: LICENSE
Classifier: Development Status :: 4 - Beta
Classifier: Intended Audience :: End Users/Desktop
Classifier: License :: OSI Approved :: MIT License
Classifier: Natural Language :: Chinese (Simplified)
Classifier: Operating System :: POSIX :: Linux
Classifier: Programming Language :: Python :: 3
Classifier: Programming Language :: Python :: 3.10
Classifier: Programming Language :: Python :: 3.11
Classifier: Programming Language :: Python :: 3.12
Classifier: Programming Language :: Python :: 3.13
Classifier: Topic :: Multimedia :: Video
Requires-Python: >=3.10
Requires-Dist: aiohttp
Requires-Dist: brotli
Requires-Dist: browser-cookie3
Requires-Dist: keyring
Requires-Dist: pillow
Requires-Dist: pure-protobuf
Requires-Dist: pyqt6
Requires-Dist: qasync
Requires-Dist: qrcode
Provides-Extra: test
Requires-Dist: coverage; extra == 'test'
Requires-Dist: ipdb; extra == 'test'
Requires-Dist: pytest; extra == 'test'
Requires-Dist: ruff; extra == 'test'
Requires-Dist: ty; extra == 'test'
